cubix/__init__.py
cubix/__main__.py
cubix/clouds.py
cubix/playground.py
cubix/utils.py
cubix-1.1.1.dist-info/METADATA
cubix-1.1.1.dist-info/WHEEL
cubix-1.1.1.dist-info/top_level.txt
cubix-1.1.1.dist-info/RECORD
