Metadata-Version: 2.1
Name: cubix
Version: 1.1.1
Summary: Persistent homology using KDE
Requires-Python: >=3.10
Requires-Dist: numpy>=2.2.0
Requires-Dist: scipy>=1.14.1
Provides-Extra: plot
Requires-Dist: matplotlib>=3.9.3; extra == "plot"
Provides-Extra: gui
Requires-Dist: matplotlib>=3.9.3; extra == "gui"
Requires-Dist: pyqt5>=5.15.11; extra == "gui"
